sqlsprinkler/__init__.py
sqlsprinkler/api.py
sqlsprinkler/system.py
sqlsprinkler/zone.py
sqlsprinkler_python_GT3CH1-0.0.13.dist-info/LICENSE
sqlsprinkler_python_GT3CH1-0.0.13.dist-info/METADATA
sqlsprinkler_python_GT3CH1-0.0.13.dist-info/WHEEL
sqlsprinkler_python_GT3CH1-0.0.13.dist-info/top_level.txt
sqlsprinkler_python_GT3CH1-0.0.13.dist-info/RECORD
