Metadata-Version: 2.1
Name: sqlsprinkler-python-GT3CH1
Version: 0.0.13
Summary: A python library to control a SQLSprinkler system
Home-page: https://github.com/GT3CH1/sqlsprinkler_python
Author: Gavin Pease
Author-email: gavinpease@gmail.com
Project-URL: Bug Tracker, https://github.com/GT3CH1/sqlsprinkler_python/issues
Classifier: Programming Language :: Python :: 3
Classifier: License :: OSI Approved :: MIT License
Requires-Python: >=3.8
License-File: LICENSE
